{
  "statement_type": "CASH_FLOW",
  "line_items": [
    {
      "name_en": "Cash flows from operating activities",
      "name_ar": "التدفقات النقدية من الانشطة التشغيلية",
      "values": [],
      "level": 0,
      "parent_index": null,
      "is_total": false,
      "is_subtotal": false,
      "note_number": null,
      "source": {
        "table_id": "p4_t1",
        "row_index": 0,
        "page": 4
      },
      "confidence": 0.95,
      "order": 0
    },
    {
      "name_en": "Net profit for the period",
      "name_ar": "صافي ربح الفترة",
      "values": [
        {
          "fiscal_year": 2025,
          "amount": 9383411,
          "column_index": 1
        },
        {
          "fiscal_year": 2024,
          "amount": 6937710,
          "column_index": 2
        }
      ],
      "level": 1,
      "parent_index": 0,
      "is_total": false,
      "is_subtotal": false,
      "note_number": null,
      "source": {
        "table_id": "p4_t1",
        "row_index": 1,
        "page": 4
      },
      "confidence": 0.95,
      "order": 1
    },
    {
      "name_en": "Adjustments",
      "name_ar": "التعديلات",
      "values": [],
      "level": 1,
      "parent_index": 0,
      "is_total": false,
      "is_subtotal": false,
      "note_number": null,
      "source": {
        "table_id": "p4_t1",
        "row_index": 2,
        "page": 4
      },
      "confidence": 0.9,
      "order": 2
    },
    {
      "name_en": "Depreciation of property, plant and equipment",
      "name_ar": "إهلاك ممتلكات والات ومعدات",
      "values": [
        {
          "fiscal_year": 2025,
          "amount": 988272,
          "column_index": 1
        },
        {
          "fiscal_year": 2024,
          "amount": 726917,
          "column_index": 2
        }
      ],
      "level": 2,
      "parent_index": 2,
      "is_total": false,
      "is_subtotal": false,
      "note_number": null,
      "source": {
        "table_id": "p4_t1",
        "row_index": 3,
        "page": 4
      },
      "confidence": 0.95,
      "order": 3
    },
    {
      "name_en": "Provision for end of service benefits",
      "name_ar": "مخصص مكافأة نهاية الخدمة",
      "values": [
        {
          "fiscal_year": 2025,
          "amount": 60687,
          "column_index": 1
        },
        {
          "fiscal_year": 2024,
          "amount": 60687,
          "column_index": 2
        }
      ],
      "level": 2,
      "parent_index": 2,
      "is_total": false,
      "is_subtotal": false,
      "note_number": null,
      "source": {
        "table_id": "p4_t1",
        "row_index": 4,
        "page": 4
      },
      "confidence": 0.95,
      "order": 4
    },
    {
      "name_en": "Changes in working capital:",
      "name_ar": "التغير في رأس المال العامل :",
      "values": [],
      "level": 1,
      "parent_index": 0,
      "is_total": false,
      "is_subtotal": false,
      "note_number": null,
      "source": {
        "table_id": "p4_t1",
        "row_index": 5,
        "page": 4
      },
      "confidence": 0.95,
      "order": 5
    },
    {
      "name_en": "Change in accounts receivable",
      "name_ar": "التغير في العملاء",
      "values": [
        {
          "fiscal_year": 2025,
          "amount": -3422456,
          "column_index": 1
        },
        {
          "fiscal_year": 2024,
          "amount": -5779161,
          "column_index": 2
        }
      ],
      "level": 2,
      "parent_index": 5,
      "is_total": false,
      "is_subtotal": false,
      "note_number": null,
      "source": {
        "table_id": "p4_t1",
        "row_index": 6,
        "page": 4
      },
      "confidence": 0.95,
      "order": 6
    },
    {
      "name_en": "Change in other debit balances",
      "name_ar": "التغير في الأرصدة المدينة الأخرى",
      "values": [
        {
          "fiscal_year": 2025,
          "amount": 180146,
          "column_index": 1
        },
        {
          "fiscal_year": 2024,
          "amount": 37208,
          "column_index": 2
        }
      ],
      "level": 2,
      "parent_index": 5,
      "is_total": false,
      "is_subtotal": false,
      "note_number": null,
      "source": {
        "table_id": "p4_t1",
        "row_index": 7,
        "page": 4
      },
      "confidence": 0.95,
      "order": 7
    },
    {
      "name_en": "Prepaid expenses",
      "name_ar": "مصروفات مدفوعة مقدما",
      "values": [
        {
          "fiscal_year": 2025,
          "amount": -14355,
          "column_index": 1
        },
        {
          "fiscal_year": 2024,
          "amount": null,
          "column_index": 2
        }
      ],
      "level": 2,
      "parent_index": 5,
      "is_total": false,
      "is_subtotal": false,
      "note_number": null,
      "source": {
        "table_id": "p4_t1",
        "row_index": 8,
        "page": 4
      },
      "confidence": 0.95,
      "order": 8
    },
    {
      "name_en": "Change in ending inventory",
      "name_ar": "التغير في مخزون اخر المدة",
      "values": [
        {
          "fiscal_year": 2025,
          "amount": -987819,
          "column_index": 1
        },
        {
          "fiscal_year": 2024,
          "amount": -655921,
          "column_index": 2
        }
      ],
      "level": 2,
      "parent_index": 5,
      "is_total": false,
      "is_subtotal": false,
      "note_number": null,
      "source": {
        "table_id": "p4_t1",
        "row_index": 9,
        "page": 4
      },
      "confidence": 0.95,
      "order": 9
    },
    {
      "name_en": "Change in trade payables",
      "name_ar": "التغير في الدائنون التجاريون",
      "values": [
        {
          "fiscal_year": 2025,
          "amount": 1309273,
          "column_index": 1
        },
        {
          "fiscal_year": 2024,
          "amount": 564427,
          "column_index": 2
        }
      ],
      "level": 2,
      "parent_index": 5,
      "is_total": false,
      "is_subtotal": false,
      "note_number": null,
      "source": {
        "table_id": "p4_t1",
        "row_index": 10,
        "page": 4
      },
      "confidence": 0.95,
      "order": 10
    },
    {
      "name_en": "Net cash generated from operating activities",
      "name_ar": "النقد الناتج من الانشطة التشغيلية",
      "values": [
        {
          "fiscal_year": 2025,
          "amount": 6359934,
          "column_index": 1
        },
        {
          "fiscal_year": 2024,
          "amount": 1891867,
          "column_index": 2
        }
      ],
      "level": 0,
      "parent_index": null,
      "is_total": true,
      "is_subtotal": false,
      "note_number": null,
      "source": {
        "table_id": "p4_t1",
        "row_index": 12,
        "page": 4
      },
      "confidence": 0.95,
      "order": 11
    },
    {
      "name_en": "Cash flow from investing activities:",
      "name_ar": "التدفق النقدي من أنشطة الاستثمار :",
      "values": [],
      "level": 0,
      "parent_index": null,
      "is_total": false,
      "is_subtotal": false,
      "note_number": null,
      "source": {
        "table_id": "p4_t1",
        "row_index": 13,
        "page": 4
      },
      "confidence": 0.95,
      "order": 12
    },
    {
      "name_en": "Additions to property, plant and equipment",
      "name_ar": "إضافات ممتلكات والات ومعدات",
      "values": [
        {
          "fiscal_year": 2025,
          "amount": -1699140,
          "column_index": 1
        },
        {
          "fiscal_year": 2024,
          "amount": -808284,
          "column_index": 2
        }
      ],
      "level": 1,
      "parent_index": 12,
      "is_total": false,
      "is_subtotal": false,
      "note_number": null,
      "source": {
        "table_id": "p4_t1",
        "row_index": 14,
        "page": 4
      },
      "confidence": 0.95,
      "order": 13
    },
    {
      "name_en": "Projects under construction",
      "name_ar": "مشاريع تحت التنفيذ",
      "values": [
        {
          "fiscal_year": 2025,
          "amount": -468559,
          "column_index": 1
        },
        {
          "fiscal_year": 2024,
          "amount": -907729,
          "column_index": 2
        }
      ],
      "level": 1,
      "parent_index": 12,
      "is_total": false,
      "is_subtotal": false,
      "note_number": null,
      "source": {
        "table_id": "p4_t1",
        "row_index": 15,
        "page": 4
      },
      "confidence": 0.95,
      "order": 14
    },
    {
      "name_en": "Net cash generated from investing activities",
      "name_ar": "النقد الناتج من الانشطة الاستثمارية",
      "values": [
        {
          "fiscal_year": 2025,
          "amount": -2167699,
          "column_index": 1
        },
        {
          "fiscal_year": 2024,
          "amount": -1716013,
          "column_index": 2
        }
      ],
      "level": 0,
      "parent_index": null,
      "is_total": true,
      "is_subtotal": false,
      "note_number": null,
      "source": {
        "table_id": "p4_t1",
        "row_index": 16,
        "page": 4
      },
      "confidence": 0.95,
      "order": 15
    },
    {
      "name_en": "Cash flow from financing activities:",
      "name_ar": "التدفق النقدي من أنشطة التمويل :",
      "values": [],
      "level": 0,
      "parent_index": null,
      "is_total": false,
      "is_subtotal": false,
      "note_number": null,
      "source": {
        "table_id": "p4_t1",
        "row_index": 17,
        "page": 4
      },
      "confidence": 0.95,
      "order": 16
    },
    {
      "name_en": "Change in related parties - credit",
      "name_ar": "التغير في أطراف ذات علاقة - دائنة",
      "values": [
        {
          "fiscal_year": 2025,
          "amount": 6459578,
          "column_index": 1
        },
        {
          "fiscal_year": 2024,
          "amount": -197587,
          "column_index": 2
        }
      ],
      "level": 1,
      "parent_index": 16,
      "is_total": false,
      "is_subtotal": false,
      "note_number": null,
      "source": {
        "table_id": "p4_t1",
        "row_index": 18,
        "page": 4
      },
      "confidence": 0.95,
      "order": 17
    },
    {
      "name_en": "Dividends distribution",
      "name_ar": "توزيع أرباح",
      "values": [
        {
          "fiscal_year": 2025,
          "amount": -10171400,
          "column_index": 1
        },
        {
          "fiscal_year": 2024,
          "amount": null,
          "column_index": 2
        }
      ],
      "level": 1,
      "parent_index": 16,
      "is_total": false,
      "is_subtotal": false,
      "note_number": null,
      "source": {
        "table_id": "p4_t1",
        "row_index": 19,
        "page": 4
      },
      "confidence": 0.95,
      "order": 18
    },
    {
      "name_en": "Cash surplus from financing activities",
      "name_ar": "الفائض النقدي من أنشطة التمويل",
      "values": [
        {
          "fiscal_year": 2025,
          "amount": -3711822,
          "column_index": 1
        },
        {
          "fiscal_year": 2024,
          "amount": -197587,
          "column_index": 2
        }
      ],
      "level": 0,
      "parent_index": null,
      "is_total": true,
      "is_subtotal": false,
      "note_number": null,
      "source": {
        "table_id": "p4_t1",
        "row_index": 20,
        "page": 4
      },
      "confidence": 0.95,
      "order": 19
    },
    {
      "name_en": "Cash surplus during the financial period",
      "name_ar": "الفائض النقدي خلال الفترة المالية",
      "values": [
        {
          "fiscal_year": 2025,
          "amount": 480413,
          "column_index": 1
        },
        {
          "fiscal_year": 2024,
          "amount": -21733,
          "column_index": 2
        }
      ],
      "level": 0,
      "parent_index": null,
      "is_total": true,
      "is_subtotal": false,
      "note_number": null,
      "source": {
        "table_id": "p4_t1",
        "row_index": 21,
        "page": 4
      },
      "confidence": 0.95,
      "order": 20
    },
    {
      "name_en": "Cash balance at the beginning of the period",
      "name_ar": "رصيد النقد في اول المدة",
      "values": [
        {
          "fiscal_year": 2025,
          "amount": 35416,
          "column_index": 1
        },
        {
          "fiscal_year": 2024,
          "amount": 57148,
          "column_index": 2
        }
      ],
      "level": 0,
      "parent_index": null,
      "is_total": false,
      "is_subtotal": false,
      "note_number": null,
      "source": {
        "table_id": "p4_t1",
        "row_index": 22,
        "page": 4
      },
      "confidence": 0.95,
      "order": 21
    },
    {
      "name_en": "Cash balance at the end of the period",
      "name_ar": "رصيد النقد في اخر المدة",
      "values": [
        {
          "fiscal_year": 2025,
          "amount": 515829,
          "column_index": 1
        },
        {
          "fiscal_year": 2024,
          "amount": 35416,
          "column_index": 2
        }
      ],
      "level": 0,
      "parent_index": null,
      "is_total": true,
      "is_subtotal": false,
      "note_number": null,
      "source": {
        "table_id": "p4_t1",
        "row_index": 23,
        "page": 4
      },
      "confidence": 0.95,
      "order": 22
    }
  ],
  "totals": {
    "net_cash_operating": {
      "2025": 6359934,
      "2024": 1891867
    },
    "net_cash_investing": {
      "2025": -2167699,
      "2024": -1716013
    },
    "net_cash_financing": {
      "2025": -3711822,
      "2024": -197587
    },
    "net_increase_decrease_cash": {
      "2025": 480413,
      "2024": -21733
    },
    "cash_end_of_period": {
      "2025": 515829,
      "2024": 35416
    }
  },
  "extraction_notes": [
    "Row index 11 in table p4_t1 was an intermediate subtotal row without a label, excluded from line items but used for calculation verification.",
    "Arabic names extracted directly from table rows.",
    "English names translated from Arabic context."
  ],
  "confidence": 0.96
}